scalar_fastapi/__init__.py
scalar_fastapi/py.typed
scalar_fastapi/scalar_fastapi.py
scalar_fastapi-1.5.0.dist-info/METADATA
scalar_fastapi-1.5.0.dist-info/WHEEL
scalar_fastapi-1.5.0.dist-info/top_level.txt
scalar_fastapi-1.5.0.dist-info/RECORD
