Metadata-Version: 2.4
Name: scalar_fastapi
Version: 1.5.0
Summary: This plugin provides an easy way to render a beautiful API reference based on a OpenAPI/Swagger file with FastAPI.
Home-page: https://github.com/scalar/scalar
Author: Scalar
Author-email: support@scalar.com
Dynamic: author
Dynamic: author-email
Dynamic: description
Dynamic: description-content-type
Dynamic: home-page
Dynamic: summary
